hypella_indicators/__init__.py
hypella_indicators/core.py
hypella_indicators/indicators/__init__.py
hypella_indicators/indicators/adx.py
hypella_indicators/indicators/atr.py
hypella_indicators/indicators/bb.py
hypella_indicators/indicators/candle.py
hypella_indicators/indicators/ema.py
hypella_indicators/indicators/price.py
hypella_indicators/indicators/rsi.py
hypella_indicators/indicators/rsi_sma.py
hypella_indicators/indicators/sma.py
hypella_indicators/indicators/volume_sma.py
hypella_indicators/registry.yaml
hypella_indicators-1.3.0.dist-info/METADATA
hypella_indicators-1.3.0.dist-info/WHEEL
hypella_indicators-1.3.0.dist-info/licenses/LICENSE
hypella_indicators-1.3.0.dist-info/RECORD
