Metadata-Version: 2.4
Name: hypella-indicators
Version: 1.3.0
Summary: Standard indicators library for the Hypella execution platform
License-Expression: MIT
License-File: LICENSE
Keywords: trading,crypto,hyperliquid,algo,indicators
Author: Hypella Team
Author-email: dev@hypella.com
Requires-Python: >=3.9
Classifier: Development Status :: 3 - Alpha
Classifier: Intended Audience :: Developers
Classifier: Intended Audience :: Financial and Insurance Industry
Classifier: License :: OSI Approved :: MIT License
Classifier: Programming Language :: Python :: 3
Classifier: Programming Language :: Python :: 3.9
Classifier: Programming Language :: Python :: 3.10
Classifier: Programming Language :: Python :: 3.11
Classifier: Topic :: Office/Business :: Financial :: Investment
Requires-Dist: numpy (>=1.20.0)
Requires-Dist: pandas (>=2.0.0)
Project-URL: Documentation, https://github.com/hypella/hypella-indicators#readme
Project-URL: Issues, https://github.com/hypella/hypella-indicators/issues
Project-URL: Source, https://github.com/hypella/hypella-indicators
